chatter/__init__.py
chatter/admin.py
chatter/apps.py
chatter/consumers.py
chatter/forms.py
chatter/messages.py
chatter/models.py
chatter/routings.py
chatter/urls.py
chatter/views.py
chatter/api/__init__.py
chatter/api/serializers.py
chatter/api/urls.py
chatter/api/views.py
chatter/migrations/0001_initial.py
chatter/migrations/0002_auto_20200922_1209.py
chatter/migrations/0003_auto_20200922_1221.py
chatter/migrations/0004_auto_20200925_1757.py
chatter/migrations/0005_auto_20200925_1856.py
chatter/migrations/0006_auto_20201007_2130.py
chatter/migrations/0007_auto_20201014_1455.py
chatter/migrations/__init__.py
chatter/static/admin/change_form.html
chatter/static/admin/css/autocomplete.css
chatter/static/admin/css/base.css
chatter/static/admin/css/changelists.css
chatter/static/admin/css/dashboard.css
chatter/static/admin/css/fonts.css
chatter/static/admin/css/forms.css
chatter/static/admin/css/login.css
chatter/static/admin/css/nav_sidebar.css
chatter/static/admin/css/responsive.css
chatter/static/admin/css/responsive_rtl.css
chatter/static/admin/css/rtl.css
chatter/static/admin/css/widgets.css
chatter/static/admin/css/vendor/select2/select2.css
chatter/static/admin/css/vendor/select2/select2.min.css
chatter/static/admin/img/calendar-icons.svg
chatter/static/admin/img/icon-addlink.svg
chatter/static/admin/img/icon-alert.svg
chatter/static/admin/img/icon-calendar.svg
chatter/static/admin/img/icon-changelink.svg
chatter/static/admin/img/icon-clock.svg
chatter/static/admin/img/icon-deletelink.svg
chatter/static/admin/img/icon-no.svg
chatter/static/admin/img/icon-unknown-alt.svg
chatter/static/admin/img/icon-unknown.svg
chatter/static/admin/img/icon-viewlink.svg
chatter/static/admin/img/icon-yes.svg
chatter/static/admin/img/inline-delete.svg
chatter/static/admin/img/search.svg
chatter/static/admin/img/selector-icons.svg
chatter/static/admin/img/sorting-icons.svg
chatter/static/admin/img/tooltag-add.svg
chatter/static/admin/img/tooltag-arrowright.svg
django_chats-0.2.2.dist-info/AUTHORS.rst
django_chats-0.2.2.dist-info/LICENSE
django_chats-0.2.2.dist-info/METADATA
django_chats-0.2.2.dist-info/WHEEL
django_chats-0.2.2.dist-info/top_level.txt
django_chats-0.2.2.dist-info/RECORD
