Metadata-Version: 2.1
Name: django-chats
Version: 0.2.2
Summary: Async Chatter App Based on Webscokets
Home-page: https://github.com/Ming-Lyu/chatter
Author: MingLyu
Author-email: minglyupolimi@gmail.com
License: MIT
Keywords: chatter
Platform: UNKNOWN
Classifier: Development Status :: 3 - Alpha
Classifier: Framework :: Django :: 3.1
Classifier: Intended Audience :: Developers
Classifier: License :: OSI Approved :: BSD License
Classifier: Natural Language :: English
Classifier: Programming Language :: Python :: 3.7
Classifier: Programming Language :: Python :: 3.8
Requires-Dist: django (==3.0)
Requires-Dist: django-fsm
Requires-Dist: djangorestframework
Requires-Dist: django-environ
Requires-Dist: channels-redis
Requires-Dist: channels
Requires-Dist: daphne
